ib110hw/__init__.py
ib110hw/automaton/__init__.py
ib110hw/automaton/base.py
ib110hw/automaton/dfa.py
ib110hw/automaton/nfa.py
ib110hw/automaton/utils.py
ib110hw/turing/__init__.py
ib110hw/turing/_helpers.py
ib110hw/turing/base.py
ib110hw/turing/dtm.py
ib110hw/turing/mtm.py
ib110hw/turing/tape.py
ib110hw/turing/utils.py
ib110hw-0.1.7.dist-info/LICENSE
ib110hw-0.1.7.dist-info/METADATA
ib110hw-0.1.7.dist-info/WHEEL
ib110hw-0.1.7.dist-info/top_level.txt
ib110hw-0.1.7.dist-info/RECORD
