Metadata-Version: 2.1
Name: ib110hw
Version: 0.1.7
Summary: UNKNOWN
Home-page: https://github.com/pilatmartin/ib110hw
Author: Martin Pilát
Author-email: 8pilatmartin8@gmail.com
License: UNKNOWN
Platform: UNKNOWN
Classifier: Programming Language :: Python :: 3
Classifier: License :: OSI Approved :: MIT License
Classifier: Operating System :: OS Independent
License-File: LICENSE
Requires-Dist: pynput
